{
  "addons": {
    "NSQC": {
      "link": "https://github.com/Vladgobelen/NSQC/archive/refs/heads/main.zip",
      "description": "Гильдейский аддон для Ночной стражи",
      "type": 0,
      "source_path": "NSQC-main/",
      "target_path": "Interface/AddOns/NSQC/"
    },
    "WDM": {
      "link": "https://github.com/Trimitor/WDM-addons/archive/refs/heads/main.zip",
      "description": "Аддон карт подземелий",
      "type": 0,
      "source_path": "WDM-addons-main/WDM/",
      "target_path": "Interface/AddOns/WDM/"
    },
    "Fonts": {
      "link": "https://hub.mos.ru/vladgobelen/nsqcmap/-/raw/main/Fonts.zip",
      "description": "Шрифты для квестов",
      "type": 2,
      "source_path": "",
      "target_path": "Fonts/"
    },
    "Patch": {
      "link": "https://hub.mos.ru/vladgobelen/nsqcmap/-/raw/main/patch-ruRU-M.MPQ",
      "description": "Патч локализации",
      "type": 1,
      "source_path": "",
      "target_path": "Data/ruRU/patch-ruRU-M.MPQ"
    }
  }
}
